dharitrietl/__main__.py
dharitrietl/constants.py
dharitrietl/errors.py
dharitrietl/indexer.py
dharitrietl/logger.py
dharitrietl/schema.py
dharitrietl/schema_test.py
dharitrietl/cli/__init__.py
dharitrietl/cli/plan_tasks.py
dharitrietl/cli/schema.py
dharitrietl/cli/work.py
dharitrietl/jobs/__init__.py
dharitrietl/jobs/extract_job.py
dharitrietl/jobs/extract_job_test.py
dharitrietl/jobs/file_storage.py
dharitrietl/jobs/load_job.py
dharitrietl/jobs/load_job_test.py
dharitrietl/jobs/transform_job.py
dharitrietl/jobs/transform_job_test.py
dharitrietl/planner/__init__.py
dharitrietl/planner/tasks.py
dharitrietl/planner/tasks_planner.py
dharitrietl/planner/tasks_planner_test.py
dharitrietl/planner/tasks_storage.py
dharitrietl/planner/tasks_storage_test.py
dharitrietl/testdata/.gitkeep
dharitri_etl-0.1.0.dist-info/METADATA
dharitri_etl-0.1.0.dist-info/WHEEL
dharitri_etl-0.1.0.dist-info/entry_points.txt
dharitri_etl-0.1.0.dist-info/licenses/LICENSE
dharitri_etl-0.1.0.dist-info/RECORD
