Metadata-Version: 2.4
Name: dharitri-etl
Version: 0.1.0
Project-URL: Homepage, https://github.com/jaiChauhan009/dharitri-etl
Author: DharitrI
License-Expression: MIT
License-File: LICENSE
Classifier: License :: OSI Approved :: MIT License
Classifier: Operating System :: OS Independent
Classifier: Programming Language :: Python :: 3
Requires-Python: >=3.8
